superClass/__init__.py
superClass-0.4.dist-info/LICENSE
superClass-0.4.dist-info/METADATA
superClass-0.4.dist-info/WHEEL
superClass-0.4.dist-info/top_level.txt
superClass-0.4.dist-info/RECORD
