Metadata-Version: 2.1
Name: superClass
Version: 0.4
Summary: superClasses GroupI implementation
Home-page: https://github.com/groupI/res/python/superClass
Author: Wise Man
Author-email: jdgrillet22@gmail.com
License: UNKNOWN
Platform: UNKNOWN
Classifier: Programming Language :: Python :: 3
Classifier: License :: OSI Approved :: MIT License
Classifier: Operating System :: OS Independent
